pts_st9010a_hipot_tester/__init__.py
pts_st9010a_hipot_tester/st9010a_hipot_tester.py
pts_st9010a_hipot_tester-0.0.2.dist-info/LICENSE.txt
pts_st9010a_hipot_tester-0.0.2.dist-info/METADATA
pts_st9010a_hipot_tester-0.0.2.dist-info/WHEEL
pts_st9010a_hipot_tester-0.0.2.dist-info/top_level.txt
pts_st9010a_hipot_tester-0.0.2.dist-info/RECORD
