Metadata-Version: 2.1
Name: pts-st9010a-hipot-tester
Version: 0.0.2
Summary: ST9010A Hipot Tester Driver
Home-page: https://gitlab.com/pass-testing-solutions/st9010a-hipot-tester
Author: Pass testing Solutions GmbH
Author-email: shuparna@pass-testing.de
License: MIT
Platform: UNKNOWN
Classifier: License :: OSI Approved :: MIT License
Classifier: Programming Language :: Python :: 3
Classifier: Programming Language :: Python :: 3.9
License-File: LICENSE.txt
Requires-Dist: pyserial (==3.5)
